moontour_common/__init__.py
moontour_common/commands/__init__.py
moontour_common/commands/base_room_commands.py
moontour_common/commands/redis_room_commands.py
moontour_common/database/__init__.py
moontour_common/database/mongo.py
moontour_common/database/rabbitmq.py
moontour_common/database/redis.py
moontour_common/models/__init__.py
moontour_common/models/coordinates.py
moontour_common/models/guess.py
moontour_common/models/location.py
moontour_common/models/user.py
moontour_common/models/game_messages/__init__.py
moontour_common/models/game_messages/finish_phase_message.py
moontour_common/models/game_messages/game_message.py
moontour_common/models/game_messages/guess_message.py
moontour_common/models/game_messages/start_game_message.py
moontour_common/models/game_messages/start_phase_message.py
moontour_common/models/rooms/__init__.py
moontour_common/models/rooms/phase.py
moontour_common/models/rooms/room.py
moontour_common/models/rooms/room_model.py
moontour_common/models/rooms/rooms_repository.py
moontour_common/models/rooms/game_modes/__init__.py
moontour_common/models/rooms/game_modes/health_room.py
moontour_common/models/rooms/game_modes/race_room.py
moontour_common/models/rooms/game_modes/streak_room.py
moontour_common/models/rooms/participants/__init__.py
moontour_common/models/rooms/participants/participant.py
moontour_common/models/rooms/participants/player.py
moontour_common/models/rooms/participants/team.py
moontour_common-1.0.30.dist-info/METADATA
moontour_common-1.0.30.dist-info/WHEEL
moontour_common-1.0.30.dist-info/RECORD
